README.md
setup.py
smashbot/__init__.py
smashbot/bot_id.py
smashbot/slackpi.py
smashbot/testit.py
smashbot.egg-info/PKG-INFO
smashbot.egg-info/SOURCES.txt
smashbot.egg-info/dependency_links.txt
smashbot.egg-info/top_level.txt
smashbot/harrison/__init__.py
smashbot/harrison/slacklib.py
smashbot/wray/__init__.py
smashbot/wray/led.py
smashbot/wray/slacklib.py
smashbot/wray/temp_humidity.py