Metadata-Version: 1.1
Name: smashbot
Version: 0.1.516583334
Summary: Python Code for Slackbot Tech Training Demo
Home-page: https://github.com/wray/slack_smashbot
Author: Wray Mills
Author-email: wray@wrayesian.com
License: UNKNOWN
Download-URL: https://github.com/wray/slack_smashbot/tarball/0.1.516583334
Keywords: slackbot,RPi,AWS
Platform: UNKNOWN
